genesis/__init__.py
genesis/_cain.so
genesis/_common.so
genesis/_eva.so
genesis/cain.py
genesis/common.py
genesis/eva.py
genesis/__pycache__/__init__.cpython-35.pyc
genesis/__pycache__/cain.cpython-35.pyc
genesis/__pycache__/eva.cpython-35.pyc
genesis/meta/architectures.xml
genesis/meta/links.xml
genesis/meta/schemes.xml
GeNESiS_SDK-0.1.12.dist-info/AUTHORS
GeNESiS_SDK-0.1.12.dist-info/LICENSE.rst
GeNESiS_SDK-0.1.12.dist-info/METADATA
GeNESiS_SDK-0.1.12.dist-info/WHEEL
GeNESiS_SDK-0.1.12.dist-info/top_level.txt
GeNESiS_SDK-0.1.12.dist-info/RECORD
