Metadata-Version: 2.1
Name: GeNESiS-SDK
Version: 0.1.12
Summary: UNKNOWN
Home-page: https://www.bsc.es/
Maintainer: juan.rodriguez
Maintainer-email: juan.rodriguez@bsc.es
License: To be defined
Download-URL: http://GeNESiS.bsc.es
Keywords: HPC, Hererogeneous Computing, Geophysics
Platform: Linux
Classifier: Development Status :: 3 - Alpha
Classifier: License :: Free for non-commercial use
Classifier: Intended Audience :: Science/Research
Classifier: Intended Audience :: Developers
Classifier: Programming Language :: Python :: 3.5
Classifier: Topic :: Scientific/Engineering
Classifier: Topic :: Software Development :: Libraries
Classifier: Operating System :: POSIX :: Linux
Requires-Dist: numpy
